python_package_plaw/__init__.py
python_package_plaw/maths.py
python_package_plaw-0.1.0.dist-info/LICENCE
python_package_plaw-0.1.0.dist-info/METADATA
python_package_plaw-0.1.0.dist-info/WHEEL
python_package_plaw-0.1.0.dist-info/top_level.txt
python_package_plaw-0.1.0.dist-info/RECORD
